LICENSE.md
README.md
setup.py
pumpkin_instrument/__init__.py
pumpkin_instrument/instrument.py
pumpkin_instrument/prologix.py
pumpkin_instrument/types.py
pumpkin_instrument/util.py
pumpkin_instrument.egg-info/PKG-INFO
pumpkin_instrument.egg-info/SOURCES.txt
pumpkin_instrument.egg-info/dependency_links.txt
pumpkin_instrument.egg-info/requires.txt
pumpkin_instrument.egg-info/top_level.txt
pumpkin_instrument/dmm/__init__.py
pumpkin_instrument/dmm/agilent.py
pumpkin_instrument/dmm/human.py
pumpkin_instrument/dmm/types.py
pumpkin_instrument/load/__init__.py
pumpkin_instrument/load/hpload.py
pumpkin_instrument/load/human.py
pumpkin_instrument/load/rigol.py
pumpkin_instrument/load/tekpower.py
pumpkin_instrument/load/types.py
pumpkin_instrument/pressure/__init__.py
pumpkin_instrument/pressure/gp.py
pumpkin_instrument/pressure/types.py
pumpkin_instrument/psu/__init__.py
pumpkin_instrument/psu/hppsu.py
pumpkin_instrument/psu/human.py
pumpkin_instrument/psu/korad.py
pumpkin_instrument/psu/types.py
pumpkin_instrument/switch/__init__.py
pumpkin_instrument/switch/hpswitch.py
pumpkin_instrument/switch/types.py
pumpkin_instrument/temperature/__init__.py
pumpkin_instrument/temperature/sr630.py
pumpkin_instrument/temperature/types.py
tests/__init__.py
tests/test_dmm.py