Metadata-Version: 2.1
Name: pumpkin-instrument
Version: 0.3.0
Summary: A library to interface with Pumpkin Test Equipment/Instruments.
Home-page: https://gitlab.com/pumpkin-space-systems/irad/instrument
Author: James Womack
Author-email: info@pumpkininc.com
License: UNKNOWN
Platform: UNKNOWN
Classifier: Programming Language :: Python :: 3
Classifier: License :: OSI Approved :: MIT License
Classifier: Operating System :: OS Independent
Requires-Python: >=3.7
License-File: LICENSE.md
